setup.py
examples/__init__.py
pipetool/__init__.py
pipetool/cli.py
pipetool/version.py
pipetool.egg-info/PKG-INFO
pipetool.egg-info/SOURCES.txt
pipetool.egg-info/dependency_links.txt
pipetool.egg-info/requires.txt
pipetool.egg-info/top_level.txt
pipetool/fileio/__init__.py
pipetool/fileio/file_client.py
pipetool/fileio/io.py
pipetool/fileio/parse.py
pipetool/fileio/handlers/__init__.py
pipetool/fileio/handlers/base.py
pipetool/fileio/handlers/csv_handler.py
pipetool/fileio/handlers/json_handler.py
pipetool/fileio/handlers/jsons_handler.py
pipetool/fileio/handlers/pickle_handler.py
pipetool/fileio/handlers/texts_handler.py
pipetool/fileio/handlers/tsv_handler.py
pipetool/fileio/handlers/xls_handler.py
pipetool/fileio/handlers/yaml_handler.py
pipetool/utils/__init__.py
pipetool/utils/config.py
pipetool/utils/logger.py
pipetool/utils/logging.py
pipetool/utils/misc.py
pipetool/utils/path.py
pipetool/utils/progressbar.py
pipetool/utils/registry.py
pipetool/utils/sim.py
pipetool/utils/testing.py
pipetool/utils/timer.py
pipetool/utils/utils.py
pipetool/utils/version_utils.py