Metadata-Version: 2.1
Name: pipetool
Version: 0.0.30
Summary: 基础工具集，统一文件读写，规范流行线过程
Home-page: https://gitee.com/zhys513/pipetool
Author: zhys513
Author-email: 254851907@qq.com
License: UNKNOWN
Platform: UNKNOWN
Requires-Python: >=3.6
